rdfproxy/__init__.py
rdfproxy/adapter.py
rdfproxy/constructor.py
rdfproxy/mapper.py
rdfproxy/sparqlwrapper.py
rdfproxy/utils/__init__.py
rdfproxy/utils/_types.py
rdfproxy/utils/exceptions.py
rdfproxy/utils/mapper_utils.py
rdfproxy/utils/model_utils.py
rdfproxy/utils/models.py
rdfproxy/utils/sparql_utils.py
rdfproxy/utils/type_utils.py
rdfproxy/utils/utils.py
rdfproxy/utils/checkers/_model_checks.py
rdfproxy/utils/checkers/item_checker.py
rdfproxy/utils/checkers/model_checker.py
rdfproxy/utils/checkers/query_checker.py
rdfproxy-0.9.0.dist-info/METADATA
rdfproxy-0.9.0.dist-info/WHEEL
rdfproxy-0.9.0.dist-info/licenses/LICENSE
rdfproxy-0.9.0.dist-info/RECORD
