Metadata-Version: 2.4
Name: rdfproxy
Version: 0.9.0
Author-email: Birger Schacht <birger.schacht@oeaw.ac.at>, Lukas Plank <lukas.plank@oeaw.ac.at>
License-File: LICENSE
Requires-Python: ~=3.11
Requires-Dist: httpx<0.29,>=0.28.1
Requires-Dist: pandas<3,>=2.2.3
Requires-Dist: pydantic<3,>=2.9.2
Requires-Dist: rdflib<8,>=7.1.1
